{
  "name": "ComputationalPathologyLab QuPath Catalog",
  "description": "Custom QuPath extension catalog for ComputationalPathologyLab extensions.",
  "extensions": [
    {
      "name": "VeSpA",
      "description": "A QuPath extension for automatic vessel segmentation and morphometric quantification in whole-slide images.",
      "author": "ComputationalPathologyLab",
      "homepage": "https://github.com/ComputationalPathologyLab/VeSpA",
      "releases": [
        {
          "name": "v0.1.0",
          "main_url": "https://github.com/ComputationalPathologyLab/VeSpA/releases/download/v0.1.0/qupath-extension-vespa-0.1.0.jar",
          "version_range": {
            "min": "v0.6.0"
          }
        }
      ]
    }
  ]
}
